microfpga/__init__.py
microfpga/_tests/__init__.py
microfpga/_tests/test_controller.py
microfpga/_tests/test_regint.py
microfpga/_tests/test_signals.py
microfpga/controller.py
microfpga/regint.py
microfpga/signals.py
microfpga-3.1.2.dist-info/LICENSE.txt
microfpga-3.1.2.dist-info/METADATA
microfpga-3.1.2.dist-info/WHEEL
microfpga-3.1.2.dist-info/RECORD
